talk_to_a_file-0.0.2.dist-info/licenses/LICENSE
ttf/__init__.py
ttf/talk.py
ttf/utils.py
talk_to_a_file-0.0.2.dist-info/METADATA
talk_to_a_file-0.0.2.dist-info/WHEEL
talk_to_a_file-0.0.2.dist-info/entry_points.txt
talk_to_a_file-0.0.2.dist-info/top_level.txt
talk_to_a_file-0.0.2.dist-info/RECORD
