Metadata-Version: 2.4
Name: talk-to-a-file
Version: 0.0.2
Summary: Simple CLI to talk to a file
Author-email: Deven Mistry <masterdeven@gmail.com>
License: MIT License
Keywords: anthropic,pypdf,click
Classifier: Development Status :: 4 - Beta
Classifier: Programming Language :: Python
Requires-Python: >=3.8
License-File: LICENSE
Requires-Dist: click
Requires-Dist: PyPDF2
Requires-Dist: anthropic
Requires-Dist: rich
Provides-Extra: dev
Requires-Dist: pytest; extra == "dev"
Requires-Dist: mkdocs-material; extra == "dev"
Requires-Dist: mkdocstrings[python]; extra == "dev"
Requires-Dist: pytest; extra == "dev"
Dynamic: license-file
